odoo9_addon_delivery_weight_uom_not_required-9.0.1.0.0.99.dev1-py2.7-nspkg.pth
odoo9_addon_delivery_weight_uom_not_required-9.0.1.0.0.99.dev1.dist-info/METADATA
odoo9_addon_delivery_weight_uom_not_required-9.0.1.0.0.99.dev1.dist-info/RECORD
odoo9_addon_delivery_weight_uom_not_required-9.0.1.0.0.99.dev1.dist-info/WHEEL
odoo9_addon_delivery_weight_uom_not_required-9.0.1.0.0.99.dev1.dist-info/namespace_packages.txt
odoo9_addon_delivery_weight_uom_not_required-9.0.1.0.0.99.dev1.dist-info/top_level.txt
odoo_addons/delivery_weight_uom_not_required/README.rst
odoo_addons/delivery_weight_uom_not_required/__init__.py
odoo_addons/delivery_weight_uom_not_required/__openerp__.py
odoo_addons/delivery_weight_uom_not_required/i18n/delivery_weight_uom_not_required.pot
odoo_addons/delivery_weight_uom_not_required/models/__init__.py
odoo_addons/delivery_weight_uom_not_required/models/stock_move.py
odoo_addons/delivery_weight_uom_not_required/models/stock_picking.py
odoo_addons/delivery_weight_uom_not_required/static/description/icon.png
