Metadata-Version: 2.1
Name: odoo9-addon-delivery-weight-uom-not-required
Version: 9.0.1.0.0.99.dev1
Summary: This module defines the Weight's UoM as not required.
Home-page: https://github.com/OCA/stock-logistics-workflow
Author: Eficent,Odoo Community Association (OCA)
Author-email: support@odoo-community.org
License: AGPL-3
Platform: UNKNOWN
Classifier: Programming Language :: Python
Classifier: Framework :: Odoo
Classifier: License :: OSI Approved :: GNU Affero General Public License v3
Requires-Python: ~=2.7
Requires-Dist: odoo (<9.1a,>=9.0a)
